{
  "navigationBarTitleText": "🎰 幸运抽奖",
  "navigationBarBackgroundColor": "#f7931e",
  "navigationBarTextStyle": "white",
  "enablePullDownRefresh": true,
  "onReachBottomDistance": 50,
  "backgroundTextStyle": "light",
  "backgroundColor": "#f7931e",
  "usingComponents": {
    "popup-banner": "/components/popup-banner/popup-banner",
    "lottery-activity": "/components/lottery-activity/lottery-activity",
    "t-loading": "/miniprogram_npm/tdesign-miniprogram/loading/loading",
    "t-empty": "/miniprogram_npm/tdesign-miniprogram/empty/empty",
    "custom-navbar": "/components/custom-navbar/custom-navbar"
  },
  "componentPlaceholder": {
    "popup-banner": "view",
    "lottery-activity": "view"
  },
  "navigationStyle": "custom",
  "disableScroll": true
}
